{
  "symbol": "ETHUSDT",
  "label_type": "label_kurtosis",
  "regime": "settlement",
  "train_end": "2024-12-31",
  "test_start": "2025-01-01",
  "evaluated_utc": "2026-05-16T18:01:42.529244+00:00",
  "n_train": 18931,
  "n_oos": 4685,
  "auc_in_sample": 0.546909472131888,
  "auc_holdout_train": 0.48469766463286346,
  "auc_oos": 0.6416291854892711,
  "auc_gap": -0.09471971335738305,
  "pr_auc_oos": 0.62544631058781,
  "auc_phase4_baseline": 0.6416291854892711,
  "status": "ok",
  "walk_forward_auc_mean_train": 0.546909472131888,
  "pr_auc_in_sample_cv": 0.5428554736123059,
  "accuracy_oos": 0.6014941302027749,
  "f1_oos": 0.5372986369268897,
  "pr_auc_phase4_baseline": 0.62544631058781,
  "baseline_minus_fresh_oos": 0.0
}